context_engine/__init__.py
context_engine/cli.py
context_engine/ui.py
context_engine/commands/__init__.py
context_engine/commands/add_docs.py
context_engine/commands/baseline_commands.py
context_engine/commands/bundle_command.py
context_engine/commands/checklist.py
context_engine/commands/compress_command.py
context_engine/commands/config_commands.py
context_engine/commands/export.py
context_engine/commands/init.py
context_engine/commands/init_command.py
context_engine/commands/langchain_cmd.py
context_engine/commands/reindex.py
context_engine/commands/search.py
context_engine/commands/session.py
context_engine/commands/session_commands.py
context_engine/commands/start_session_command.py
context_engine/commands/status.py
context_engine/commands/stop_session_command.py
context_engine/commands/sync.py
context_engine/compressors/__init__.py
context_engine/compressors/compress_src.py
context_engine/compressors/longcodezip_wrapper.py
context_engine/core/__init__.py
context_engine/core/ai_summary.py
context_engine/core/auto_architecture.py
context_engine/core/config.py
context_engine/core/logger.py
context_engine/core/session_tracker.py
context_engine/core/summary.py
context_engine/core/task_manager.py
context_engine/core/utils.py
context_engine/langchain/__init__.py
context_engine/langchain/enhanced_summarizer.py
context_engine/models/__init__.py
context_engine/models/openrouter.py
context_engine/parsers/__init__.py
context_engine/parsers/base_parser.py
context_engine/parsers/generic_parser.py
context_engine/parsers/java_parser.py
context_engine/parsers/js_parser.py
context_engine/parsers/parser_factory.py
context_engine/parsers/python_parser.py
context_engine/scripts/__init__.py
context_engine/scripts/auto_capture.py
context_engine/scripts/cli.py
context_engine/scripts/embedder.py
context_engine/scripts/embeddings_store.py
context_engine/scripts/export.py
context_engine/scripts/handoff_notes.py
context_engine/scripts/log_capture.py
context_engine/scripts/session.py
context_engine_dev-1.2.0.dist-info/licenses/LICENSE
context_engine_dev-1.2.0.dist-info/METADATA
context_engine_dev-1.2.0.dist-info/WHEEL
context_engine_dev-1.2.0.dist-info/entry_points.txt
context_engine_dev-1.2.0.dist-info/top_level.txt
context_engine_dev-1.2.0.dist-info/RECORD
