Metadata-Version: 2.4
Name: context-engine-dev
Version: 1.2.0
Summary: Context Engine CLI - Compress the Chaos
Home-page: https://github.com/gurram46/Context-Engine
Author: Context Engine Team
Project-URL: Bug Reports, https://github.com/gurram46/Context-Engine/issues
Project-URL: Source, https://github.com/gurram46/Context-Engine
Project-URL: Documentation, https://github.com/gurram46/Context-Engine/blob/main/README.md
Keywords: context,compression,cli,ai,documentation,productivity
Classifier: Development Status :: 4 - Beta
Classifier: Intended Audience :: Developers
Classifier: Topic :: Software Development :: Libraries :: Python Modules
Classifier: Topic :: Software Development :: Code Generators
Classifier: License :: OSI Approved :: MIT License
Classifier: Programming Language :: Python :: 3
Classifier: Programming Language :: Python :: 3.8
Classifier: Programming Language :: Python :: 3.9
Classifier: Programming Language :: Python :: 3.10
Classifier: Programming Language :: Python :: 3.11
Classifier: Programming Language :: Python :: 3.12
Requires-Python: >=3.8
License-File: LICENSE
Requires-Dist: click>=8.0.0
Requires-Dist: tiktoken>=0.5.0
Requires-Dist: requests>=2.28.0
Requires-Dist: rich>=13.0.0
Requires-Dist: pyyaml>=6.0
Requires-Dist: openrouter>=0.2.0
Dynamic: author
Dynamic: classifier
Dynamic: description
Dynamic: description-content-type
Dynamic: home-page
Dynamic: keywords
Dynamic: license-file
Dynamic: project-url
Dynamic: requires-dist
Dynamic: requires-python
Dynamic: summary
